mpf_language_server-0.1.0.dist-info/DESCRIPTION.rst
mpf_language_server-0.1.0.dist-info/METADATA
mpf_language_server-0.1.0.dist-info/RECORD
mpf_language_server-0.1.0.dist-info/WHEEL
mpf_language_server-0.1.0.dist-info/entry_points.txt
mpf_language_server-0.1.0.dist-info/metadata.json
mpf_language_server-0.1.0.dist-info/top_level.txt
mpfls/__init__.py
mpfls/__main__.py
mpfls/_utils.py
mpfls/_version.py
mpfls/lsp.py
mpfls/python_ls.py
mpfls/uris.py
mpfls/workspace.py
mpfls/config/__init__.py
mpfls/config/config.py
mpfls/config/source.py
