Metadata-Version: 2.0
Name: mpf-language-server
Version: 0.1.0
Summary: MPF Language Server
Home-page: https://github.com/missionpinball/mpf-ls
Author: Jan Kantert
Author-email: UNKNOWN
License: UNKNOWN
Platform: UNKNOWN
Requires-Dist: future (>=0.14.0)
Requires-Dist: python-jsonrpc-server (>=0.1.0)
